<annotation>
	<folder>raw</folder>
	<filename>780699415766778386297885204904796821.png</filename>
	<path>/Users/admin/Desktop/captcha/data/raw/780699415766778386297885204904796821.png</path>
	<source>
		<database>Unknown</database>
	</source>
	<size>
		<width>300</width>
		<height>150</height>
		<depth>3</depth>
	</size>
	<segmented>0</segmented>
	<object>
		<name>w</name>
		<pose>Unspecified</pose>
		<truncated>0</truncated>
		<difficult>0</difficult>
		<bndbox>
			<xmin>5</xmin>
			<ymin>39</ymin>
			<xmax>32</xmax>
			<ymax>64</ymax>
		</bndbox>
	</object>
	<object>
		<name>h</name>
		<pose>Unspecified</pose>
		<truncated>0</truncated>
		<difficult>0</difficult>
		<bndbox>
			<xmin>30</xmin>
			<ymin>38</ymin>
			<xmax>50</xmax>
			<ymax>66</ymax>
		</bndbox>
	</object>
	<object>
		<name>a</name>
		<pose>Unspecified</pose>
		<truncated>0</truncated>
		<difficult>0</difficult>
		<bndbox>
			<xmin>53</xmin>
			<ymin>46</ymin>
			<xmax>72</xmax>
			<ymax>67</ymax>
		</bndbox>
	</object>
	<object>
		<name>t</name>
		<pose>Unspecified</pose>
		<truncated>0</truncated>
		<difficult>0</difficult>
		<bndbox>
			<xmin>75</xmin>
			<ymin>41</ymin>
			<xmax>92</xmax>
			<ymax>67</ymax>
		</bndbox>
	</object>
	<object>
		<name>i</name>
		<pose>Unspecified</pose>
		<truncated>0</truncated>
		<difficult>0</difficult>
		<bndbox>
			<xmin>116</xmin>
			<ymin>36</ymin>
			<xmax>135</xmax>
			<ymax>67</ymax>
		</bndbox>
	</object>
	<object>
		<name>s</name>
		<pose>Unspecified</pose>
		<truncated>0</truncated>
		<difficult>0</difficult>
		<bndbox>
			<xmin>139</xmin>
			<ymin>43</ymin>
			<xmax>161</xmax>
			<ymax>70</ymax>
		</bndbox>
	</object>
	<object>
		<name>3</name>
		<pose>Unspecified</pose>
		<truncated>0</truncated>
		<difficult>0</difficult>
		<bndbox>
			<xmin>180</xmin>
			<ymin>39</ymin>
			<xmax>198</xmax>
			<ymax>68</ymax>
		</bndbox>
	</object>
	<object>
		<name>7</name>
		<pose>Unspecified</pose>
		<truncated>0</truncated>
		<difficult>0</difficult>
		<bndbox>
			<xmin>199</xmin>
			<ymin>39</ymin>
			<xmax>222</xmax>
			<ymax>69</ymax>
		</bndbox>
	</object>
	<object>
		<name>-</name>
		<pose>Unspecified</pose>
		<truncated>0</truncated>
		<difficult>0</difficult>
		<bndbox>
			<xmin>223</xmin>
			<ymin>49</ymin>
			<xmax>240</xmax>
			<ymax>69</ymax>
		</bndbox>
	</object>
	<object>
		<name>1</name>
		<pose>Unspecified</pose>
		<truncated>0</truncated>
		<difficult>0</difficult>
		<bndbox>
			<xmin>243</xmin>
			<ymin>39</ymin>
			<xmax>265</xmax>
			<ymax>68</ymax>
		</bndbox>
	</object>
	<object>
		<name>2</name>
		<pose>Unspecified</pose>
		<truncated>0</truncated>
		<difficult>0</difficult>
		<bndbox>
			<xmin>266</xmin>
			<ymin>40</ymin>
			<xmax>286</xmax>
			<ymax>67</ymax>
		</bndbox>
	</object>
</annotation>
